cloudengineffapi/__init__.py
cloudengineffapi/client.py
cloudengineffapi-3.1.0.dist-info/METADATA
cloudengineffapi-3.1.0.dist-info/WHEEL
cloudengineffapi-3.1.0.dist-info/top_level.txt
cloudengineffapi-3.1.0.dist-info/RECORD
