Metadata-Version: 2.4
Name: cloudengineffapi
Version: 3.1.0
Summary: Advanced SDK for CloudEngineFF APIs with thread-safe rate limiting
Author: Bijoy
Author-email: hackf1283@gmail.com
Classifier: Programming Language :: Python :: 3
Classifier: License :: OSI Approved :: MIT License
Classifier: Operating System :: OS Independent
Requires-Python: >=3.6
Requires-Dist: requests>=2.28.0
Dynamic: author
Dynamic: author-email
Dynamic: classifier
Dynamic: description
Dynamic: description-content-type
Dynamic: requires-dist
Dynamic: requires-python
Dynamic: summary
